mycalc/calculator.py
caca-0.0.1.dist-info/METADATA
caca-0.0.1.dist-info/WHEEL
caca-0.0.1.dist-info/top_level.txt
caca-0.0.1.dist-info/RECORD
