Metadata-Version: 2.1
Name: caca
Version: 0.0.1
Summary: nice calculator
Home-page: https://github.com/JangYuSeung/cal0001
Download-URL: https://github.com/JangYuSeung/cal0001/
Author: JangYuSeung
Classifier: Programming Language :: Python :: 3
